favaghost/__init__.py
favaghost/service.py
fava_ghost-0.1.13.dist-info/METADATA
fava_ghost-0.1.13.dist-info/WHEEL
fava_ghost-0.1.13.dist-info/entry_points.txt
fava_ghost-0.1.13.dist-info/top_level.txt
fava_ghost-0.1.13.dist-info/RECORD
