Metadata-Version: 2.1
Name: fava-ghost
Version: 0.1.13
Summary: A daemon for fava server and git repo sync
Home-page: https://github.com/e7h4n/fava-ghost
Author: e7h4n
Author-email: ethan.pw@icloud.com
Project-URL: Bug Reports, https://github.com/e7h4n/fava-ghost/issues
Project-URL: Source, https://github.com/e7h4n/fava-ghost/
Keywords: beancount,fava,daemon,git sync
Classifier: Development Status :: 4 - Beta
Classifier: Intended Audience :: Financial and Insurance Industry
Classifier: Topic :: Office/Business :: Financial :: Accounting
Classifier: License :: OSI Approved :: MIT License
Classifier: Programming Language :: Python :: 3
Classifier: Programming Language :: Python :: 3.6
Classifier: Programming Language :: Python :: 3.7
Classifier: Programming Language :: Python :: 3.8
Classifier: Programming Language :: Python :: 3.9
Classifier: Programming Language :: Python :: 3 :: Only
Requires-Python: >=3.6, <4
Requires-Dist: gitpython ==3.1.40
Provides-Extra: dev
Provides-Extra: test
Requires-Dist: black ; extra == 'test'
Requires-Dist: coverage ; extra == 'test'
Requires-Dist: pylint ; extra == 'test'
Requires-Dist: flake8 ; extra == 'test'
Requires-Dist: pytest ; extra == 'test'
